larixite/__init__.py
larixite/amcsd.py
larixite/amcsd_cif1.db
larixite/amcsd_utils.py
larixite/cif_cluster.py
larixite/fdmnes.py
larixite/gformat.py
larixite/physical_constants.py
larixite/struct2xas.py
larixite/utils.py
larixite/version.py
larixite/xrd_utils.py
larixite/struct/__init__.py
larixite/struct/xas.py
larixite/struct/xas_cif.py
larixite/struct/xas_xyz.py
larixite/templates/fdmnes.tmpl
larixite/templates/fdmnes_xas.tmpl
larixite/templates/feff_exafs.tmpl
larixite/webapp/__init__.py
larixite/webapp/webapp.py
larixite/webapp/static/ixas_logo.ico
larixite/webapp/static/style.css
larixite/webapp/templates/about.html
larixite/webapp/templates/index.html
larixite/webapp/templates/layout.html
larixite/webapp/templates/upload.html
larixite-2025.5.1.dist-info/licenses/LICENSE
larixite-2025.5.1.dist-info/METADATA
larixite-2025.5.1.dist-info/WHEEL
larixite-2025.5.1.dist-info/top_level.txt
larixite-2025.5.1.dist-info/RECORD
