Metadata-Version: 2.4
Name: larixite
Version: 2025.5.1
Summary: convert CIF data to inputs for XAS calculations Feff, FDMNES, etc
Author-email: Matthew Newville <newville@cars.uchicago.edu>, Mauro Rovezzi <mauro.rovezzi@esrf.fr>
License-Expression: MIT
Project-URL: Homepage,  https://github.com/xraypy/larixite
Project-URL: Documentation, https://xraypy.github.io/larixite
Project-URL: Tracker, https://github.com/xraypy/larixite/issues
Keywords: X-ray spectroscopy,Crystallography
Classifier: Development Status :: 5 - Production/Stable
Classifier: Intended Audience :: Developers
Classifier: Operating System :: OS Independent
Classifier: Programming Language :: Python :: 3.10
Classifier: Programming Language :: Python :: 3.11
Classifier: Programming Language :: Python :: 3.12
Classifier: Programming Language :: Python :: 3.13
Requires-Python: >=3.9
License-File: LICENSE
Requires-Dist: xraydb
Requires-Dist: sqlalchemy>=2
Requires-Dist: pymatgen>=2025.6.14
Requires-Dist: mp-api>=0.45.8
Requires-Dist: emmet-core>=0.84.9
Provides-Extra: web
Requires-Dist: flask; extra == "web"
Provides-Extra: jupyter
Requires-Dist: jupyterlab==3.*; extra == "jupyter"
Requires-Dist: crystal-toolkit>=2025.7.31; extra == "jupyter"
Provides-Extra: test
Requires-Dist: pytest; extra == "test"
Provides-Extra: doc
Requires-Dist: sphinx; extra == "doc"
Provides-Extra: dev
Requires-Dist: build; extra == "dev"
Requires-Dist: twine; extra == "dev"
Requires-Dist: ruff; extra == "dev"
Provides-Extra: all
Requires-Dist: larixite[dev,doc,jupyter,test,web]; extra == "all"
Dynamic: license-file
